botstarter/__init__.py
botstarter/bot.py
botstarter/util.py
botstarter/db/__init__.py
botstarter/db/base.py
botstarter/db/medias.py
botstarter/db/users.py
py_bot_starter-0.0.19.dist-info/LICENSE
py_bot_starter-0.0.19.dist-info/METADATA
py_bot_starter-0.0.19.dist-info/WHEEL
py_bot_starter-0.0.19.dist-info/top_level.txt
py_bot_starter-0.0.19.dist-info/RECORD
